transformers_visualizer/__init__.py
transformers_visualizer/errors.py
transformers_visualizer/plotting.py
transformers_visualizer/visualizer.py
transformers_visualizer/visualizers/__init__.py
transformers_visualizer/visualizers/attention.py
transformers_visualizer-0.2.2.dist-info/METADATA
transformers_visualizer-0.2.2.dist-info/LICENSE
transformers_visualizer-0.2.2.dist-info/WHEEL
transformers_visualizer-0.2.2.dist-info/RECORD
