Metadata-Version: 2.1
Name: transformers-visualizer
Version: 0.2.2
Summary: Explain your 🤗 transformers without effort! Display the internal behavior of your model.
Home-page: https://github.com/VDuchauffour/transformers-visualizer
License: Apache-2.0
Keywords: machine learning,natural language processing,nlp,explainability,transformers,model interpretability
Author: VDuchauffour
Author-email: vincent.duchauffour@proton.me
Requires-Python: >=3.8,<4.0
Classifier: Development Status :: 3 - Alpha
Classifier: Intended Audience :: Developers
Classifier: Intended Audience :: Science/Research
Classifier: License :: OSI Approved :: Apache Software License
Classifier: Programming Language :: Python :: 3
Classifier: Programming Language :: Python :: 3.8
Classifier: Programming Language :: Python :: 3.9
Classifier: Programming Language :: Python :: 3.10
Classifier: Programming Language :: Python :: 3.11
Classifier: Programming Language :: Python :: 3 :: Only
Classifier: Programming Language :: Python :: 3.10
Classifier: Programming Language :: Python :: 3.11
Classifier: Programming Language :: Python :: 3.7
Classifier: Programming Language :: Python :: 3.8
Classifier: Programming Language :: Python :: 3.9
Classifier: Topic :: Documentation :: Sphinx
Classifier: Topic :: Scientific/Engineering :: Artificial Intelligence
Classifier: Topic :: Scientific/Engineering :: Information Analysis
Classifier: Topic :: Software Development :: Libraries :: Python Modules
Classifier: Topic :: Text Processing :: Linguistic
Requires-Dist: captum (>=0.5.0)
Requires-Dist: matplotlib (>=3.5)
Requires-Dist: torchtyping (>=0.1.4)
Requires-Dist: transformers (>=4.0.0)
Project-URL: Repository, https://github.com/VDuchauffour/transformers-visualizer
